lager_pcb/__init__.py
lager_pcb/defines.py
lager_pcb/device.py
lager_pcb/main.py
lager_pcb/mux.py
lager_pcb/net.py
lager_pcb/mappers/__init__.py
lager_pcb/mappers/rigol_mso5000.py
lager_pcb-0.0.5.dist-info/METADATA
lager_pcb-0.0.5.dist-info/WHEEL
lager_pcb-0.0.5.dist-info/top_level.txt
lager_pcb-0.0.5.dist-info/RECORD
