Metadata-Version: 2.1
Name: lager_pcb
Version: 0.0.5
Summary: Lager PCB Interface
Home-page: https://github.com/lagerdata/gateway_pcb
Author: Lager Data LLC
Author-email: hello@lagerdata.com
Maintainer: Lager Data LLC
Maintainer-email: hello@lagerdata.com
License: MIT
Platform: UNKNOWN
Classifier: Development Status :: 3 - Alpha
Classifier: License :: OSI Approved :: MIT License
Classifier: Programming Language :: Python :: 3.6
Classifier: Programming Language :: Python :: 3.7
Classifier: Programming Language :: Python :: 3.8
Classifier: Programming Language :: Python :: 3.9
Classifier: Programming Language :: Python :: 3.10
Classifier: Topic :: Software Development
Requires-Python: >=3.6
